broken_display_simulator/__init__.py
broken_display_simulator/__main__.py
broken_display_simulator/py.typed
broken_display_simulator-0.1.1.dist-info/LICENSE
broken_display_simulator-0.1.1.dist-info/METADATA
broken_display_simulator-0.1.1.dist-info/WHEEL
broken_display_simulator-0.1.1.dist-info/entry_points.txt
broken_display_simulator-0.1.1.dist-info/RECORD
