Metadata-Version: 2.1
Name: broken-display-simulator
Version: 0.1.1
Summary: Simulates broken display.
Home-page: https://github.com/34j/broken-display-simulator
License: CC0 1.0 Universal
Author: 34j
Author-email: 34j.95a2p@simplelogin.com
Requires-Python: >=3.8,<4.0
Classifier: Development Status :: 2 - Pre-Alpha
Classifier: Intended Audience :: Developers
Classifier: License :: Other/Proprietary License
Classifier: Natural Language :: English
Classifier: Operating System :: OS Independent
Classifier: Programming Language :: Python :: 3
Classifier: Programming Language :: Python :: 3.8
Classifier: Programming Language :: Python :: 3.9
Classifier: Programming Language :: Python :: 3.10
Classifier: Programming Language :: Python :: 3.11
Classifier: Topic :: Software Development :: Libraries
Requires-Dist: click
Requires-Dist: pysimplegui
Project-URL: Bug Tracker, https://github.com/34j/broken-display-simulator/issues
Project-URL: Changelog, https://github.com/34j/broken-display-simulator/blob/main/CHANGELOG.md
Project-URL: Documentation, https://broken-display-simulator.readthedocs.io
Project-URL: Repository, https://github.com/34j/broken-display-simulator
